Verilog HDL/Vivado/Test/Test.srcs/sources_1/new/Chap_3_onclass.v
`timescale 1ns / 1ps
//////////////////////////////////////////////////////////////////////////////////
// Company: 
// Engineer: 
// 
// Create Date: 03/05/2026 08:22:32 AM
// Design Name: 
// Module Name: Chap_3_onclass
// Project Name: 
// Target Devices: 
// Tool Versions: 
// Description: 
// 
// Dependencies: 
// 
// Revision:
// Revision 0.01 - File Created
// Additional Comments:
// 
//////////////////////////////////////////////////////////////////////////////////


module adder4b(sum,cout,a,b,cin);
    input [3:0]a;
    input [3:0]b;
    input cin;
    output [3:0]sum;
    output cout;
    
    assign {cout, sum} = a + b + cin;
endmodule

module Comp4b(a_gt_b, a_eq_b, a_lt_b, a, b);
    input [3:0] a,b;
    output a_gt_b, a_eq_b, a_lt_b;
    
    assign a_gt_b = (a > b) ? 1:0;
    assign a_eq_b = (a == b)? 1:0;
    assign a_lt_b = (a < b)? 1:0;
endmodule

module mod10_counter(
    input clk,
    input rst,
    output reg [3:0] count
);

always @(posedge clk) 
    begin
        if(rst)
            count <= 0;
        else if(count == 9)
            count <= 0;
        else
            count <= count + 1;
    end
endmodule

module counter(
    input clk,
    input reset,
    input mode,
    output reg [3:0]count,
    output RCO
);
    assign RCO = (count == 4'b0000);
    always @(posedge clk) 
    begin
        if(!reset)
            count <= 0;
        else begin
            if(mode == 1'b0)
                count <= count + 1;
            else 
                count <= count - 1;
        end
    end
endmodule

Verilog HDL/Vivado/Test/Test.srcs/sim_1/new/Chap_3_onclass_tb.v
`timescale 1ns / 1ps
//////////////////////////////////////////////////////////////////////////////////
// Company: 
// Engineer: 
// 
// Create Date: 03/05/2026 08:29:22 AM
// Design Name: 
// Module Name: Chap_3_onclass_tb
// Project Name: 
// Target Devices: 
// Tool Versions: 
// Description: 
// 
// Dependencies: 
// 
// Revision:
// Revision 0.01 - File Created
// Additional Comments:
// 
//////////////////////////////////////////////////////////////////////////////////


module adder4b_tb();
    reg [9:0]stim;
    wire [3:0]S;
    wire C4;
    
    adder4b_tb a1(S,C4,stim[8:5],stim[4:1],stim[0]);
    initial $monitor("%t: %b %h %h %h %b", $time, C4, S, stim[8:5], stim[4:1], stim[0]);
    initial
        begin 
            for(stim = 0; stim < 512; stim = stim + 1) #10;
            #10 $finish;
        end
endmodule

module comp4b_tb();
    reg [4:0] a,b;
    wire a_gt,a_eq,a_lt;
    
    Comp4b uut(
        .a(a),
        .b(b),
        .a_gt_b(a_gt),
        .a_eq_b(a_eq),
        .a_lt_b(a_lt)
    );
    
    initial 
        $monitor("%t: A=%h, B=%h, AgtB=%b, AeqB=%b, AltB=%b", $time, a[3:0], b[3:0], a_gt, a_eq, a_lt); 
    initial
        #2000 $finish;
    initial
        begin
            #5;
            for(a = 0; a < 16; a = a+1)
                begin
                    for(b = 0; b < 16; b = b+1)
                        begin 
                            #5;
                        end
                end
        end
endmodule

module mod10_counter_tb();
    reg clk, rst;
    wire [3:0]count;
    initial begin 
       $dumpfile("dump.vcd");
       $dumpvars;
     end
     
endmodule

module counter_tb();
    reg clk, reset, mode;
    wire [3:0] count;
    wire RCO;
    
    counter uut(
        .clk(clk),
        .reset(reset),
        .mode(mode),
        .count(count),
        .RCO(RCO)
    );
    
    initial 
        begin 
            $dumpfile("counter_tb.vcd");
            $dumpvars;
        end
    initial $monitor("time=%t: reset= %b, mode= %b, count= %b, RCO= %b", $time, reset, mode, count, RCO);
    initial
        begin
            clk = 1'b0;
            forever #10 clk = ~clk;
        end
    initial
        begin
            reset = 1'b0;
            mode = 1'b0;
            #25;
            reset = 1'b1;
            #330;
            mode = 1'b1;
            #660;
            $finish;
        end
endmodule

Verilog HDL/Vivado/Test/Test.sim/sim_1/behav/xsim/counter_tb.vcd
$date
   Fri Mar  6 18:23:51 2026
$end

$version
  2024.2.0
  $dumpfile ("counter_tb.vcd") 
$end

$timescale
  1ps
$end

$scope module counter_tb $end
$var reg 1 ! clk $end
$var reg 1 " reset $end
$var reg 1 # mode $end
$var wire 4 $ count [3:0] $end
$var wire 1 % RCO $end
$scope module uut $end
$var wire 1 & clk $end
$var wire 1 ' reset $end
$var wire 1 ( mode $end
$var reg 4 ) count [3:0] $end
$var wire 1 % RCO $end
$upscope $end
$upscope $end
$enddefinitions $end

#0
$dumpvars
0!
0"
0#
bx $
x%
0&
0'
0(
bx )
$end

#10000
1!
b0 $
1%
1&
b0 )

#20000
0!
0&

#25000
1"
1'

#30000
1!
b1 $
0%
1&
b1 )

#40000
0!
0&

#50000
1!
b10 $
1&
b10 )

#60000
0!
0&

#70000
1!
b11 $
1&
b11 )

#80000
0!
0&

#90000
1!
b100 $
1&
b100 )

#100000
0!
0&

#110000
1!
b101 $
1&
b101 )

#120000
0!
0&

#130000
1!
b110 $
1&
b110 )

#140000
0!
0&

#150000
1!
b111 $
1&
b111 )

#160000
0!
0&

#170000
1!
b1000 $
1&
b1000 )

#180000
0!
0&

#190000
1!
b1001 $
1&
b1001 )

#200000
0!
0&

#210000
1!
b1010 $
1&
b1010 )

#220000
0!
0&

#230000
1!
b1011 $
1&
b1011 )

#240000
0!
0&

#250000
1!
b1100 $
1&
b1100 )

#260000
0!
0&

#270000
1!
b1101 $
1&
b1101 )

#280000
0!
0&

#290000
1!
b1110 $
1&
b1110 )

#300000
0!
0&

#310000
1!
b1111 $
1&
b1111 )

#320000
0!
0&

#330000
1!
b0 $
1%
1&
b0 )

#340000
0!
0&

#350000
1!
b1 $
0%
1&
b1 )

#355000
1#
1(

#360000
0!
0&

#370000
1!
b0 $
1%
1&
b0 )

#380000
0!
0&

#390000
1!
b1111 $
0%
1&
b1111 )

#400000
0!
0&

#410000
1!
b1110 $
1&
b1110 )

#420000
0!
0&

#430000
1!
b1101 $
1&
b1101 )

#440000
0!
0&

#450000
1!
b1100 $
1&
b1100 )

#460000
0!
0&

#470000
1!
b1011 $
1&
b1011 )

#480000
0!
0&

#490000
1!
b1010 $
1&
b1010 )

#500000
0!
0&

#510000
1!
b1001 $
1&
b1001 )

#520000
0!
0&

#530000
1!
b1000 $
1&
b1000 )

#540000
0!
0&

#550000
1!
b111 $
1&
b111 )

#560000
0!
0&

#570000
1!
b110 $
1&
b110 )

#580000
0!
0&

#590000
1!
b101 $
1&
b101 )

#600000
0!
0&

#610000
1!
b100 $
1&
b100 )

#620000
0!
0&

#630000
1!
b11 $
1&
b11 )

#640000
0!
0&

#650000
1!
b10 $
1&
b10 )

#660000
0!
0&

#670000
1!
b1 $
1&
b1 )

#680000
0!
0&

#690000
1!
b0 $
1%
1&
b0 )

#700000
0!
0&

#710000
1!
b1111 $
0%
1&
b1111 )

#720000
0!
0&

#730000
1!
b1110 $
1&
b1110 )

#740000
0!
0&

#750000
1!
b1101 $
1&
b1101 )

#760000
0!
0&

#770000
1!
b1100 $
1&
b1100 )

#780000
0!
0&

#790000
1!
b1011 $
1&
b1011 )

#800000
0!
0&

#810000
1!
b1010 $
1&
b1010 )

#820000
0!
0&

#830000
1!
b1001 $
1&
b1001 )

#840000
0!
0&

#850000
1!
b1000 $
1&
b1000 )

#860000
0!
0&

#870000
1!
b111 $
1&
b111 )

#880000
0!
0&

#890000
1!
b110 $
1&
b110 )

#900000
0!
0&

#910000
1!
b101 $
1&
b101 )

#920000
0!
0&

#930000
1!
b100 $
1&
b100 )

#940000
0!
0&

#950000
1!
b11 $
1&
b11 )

#960000
0!
0&

#970000
1!
b10 $
1&
b10 )

#980000
0!
0&

#990000
1!
b1 $
1&
b1 )

